llm_1min.py
llm_1minai-0.3.0.dist-info/licenses/LICENSE
llm_1minai-0.3.0.dist-info/METADATA
llm_1minai-0.3.0.dist-info/WHEEL
llm_1minai-0.3.0.dist-info/entry_points.txt
llm_1minai-0.3.0.dist-info/top_level.txt
llm_1minai-0.3.0.dist-info/RECORD
