Metadata-Version: 2.4
Name: llm-1minai
Version: 0.3.0
Summary: LLM plugin providing access to 66+ AI models through 1min.ai API with web search, mixed context, and persistent options
Author: gl0bal01
License: Apache-2.0
Project-URL: Homepage, https://github.com/gl0bal01/llm-1minai
Project-URL: Repository, https://github.com/gl0bal01/llm-1minai
Project-URL: Documentation, https://github.com/gl0bal01/llm-1minai#readme
Project-URL: Changelog, https://github.com/gl0bal01/llm-1minai/blob/main/CHANGELOG.md
Project-URL: Issue Tracker, https://github.com/gl0bal01/llm-1minai/issues
Project-URL: 1min.ai, https://docs.1min.ai
Keywords: llm,ai,1min.ai,gpt,claude,gemini,chatgpt,anthropic,openai
Classifier: Development Status :: 4 - Beta
Classifier: Intended Audience :: Developers
Classifier: Programming Language :: Python :: 3
Classifier: Programming Language :: Python :: 3.8
Classifier: Programming Language :: Python :: 3.9
Classifier: Programming Language :: Python :: 3.10
Classifier: Programming Language :: Python :: 3.11
Classifier: Programming Language :: Python :: 3.12
Classifier: Topic :: Software Development :: Libraries :: Python Modules
Classifier: Topic :: Scientific/Engineering :: Artificial Intelligence
Requires-Python: >=3.8
License-File: LICENSE
Requires-Dist: llm>=0.13
Requires-Dist: requests>=2.31.0
Requires-Dist: click>=8.0
Provides-Extra: test
Requires-Dist: pytest>=7.4.0; extra == "test"
Requires-Dist: pytest-cov>=4.1.0; extra == "test"
Requires-Dist: pytest-mock>=3.12.0; extra == "test"
Requires-Dist: requests-mock>=1.11.0; extra == "test"
Provides-Extra: dev
Requires-Dist: black>=23.0.0; extra == "dev"
Requires-Dist: ruff>=0.1.0; extra == "dev"
Requires-Dist: pytest>=7.4.0; extra == "dev"
Requires-Dist: pytest-cov>=4.1.0; extra == "dev"
Requires-Dist: pytest-mock>=3.12.0; extra == "dev"
Requires-Dist: requests-mock>=1.11.0; extra == "dev"
Dynamic: license-file
